MANIFEST.in
setup.py
athenaCL/__init__.py
athenaCL/athenacl.py
athenaCL.egg-info/PKG-INFO
athenaCL.egg-info/SOURCES.txt
athenaCL.egg-info/dependency_links.txt
athenaCL.egg-info/top_level.txt
athenaCL/audio/__init__.py
athenaCL/audio/cloth01.aif
athenaCL/audio/cloth02.aif
athenaCL/audio/drum01.aif
athenaCL/audio/grains01.aif
athenaCL/audio/latch01.aif
athenaCL/audio/metal01.aif
athenaCL/audio/metal02.aif
athenaCL/audio/metal03.aif
athenaCL/audio/plastic01.aif
athenaCL/audio/plastic02.aif
athenaCL/audio/wood01.aif
athenaCL/demo/__init__.py
athenaCL/demo/csound/__init__.py
athenaCL/demo/csound/script01a.mp3
athenaCL/demo/csound/script01a.py
athenaCL/demo/csound/script01b.mp3
athenaCL/demo/csound/script01b.py
athenaCL/demo/csound/script01c.mp3
athenaCL/demo/csound/script01c.py
athenaCL/demo/csound/script01d.mp3
athenaCL/demo/csound/script01d.py
athenaCL/demo/csound/script02a.mp3
athenaCL/demo/csound/script02a.py
athenaCL/demo/csound/script02b.mp3
athenaCL/demo/csound/script02b.py
athenaCL/demo/csound/script03a.mp3
athenaCL/demo/csound/script03a.py
athenaCL/demo/csound/script03b.mp3
athenaCL/demo/csound/script03b.py
athenaCL/demo/csound/script03c.mp3
athenaCL/demo/csound/script03c.py
athenaCL/demo/csound/script03d.mp3
athenaCL/demo/csound/script03d.py
athenaCL/demo/csound/script03e.mp3
athenaCL/demo/csound/script03e.py
athenaCL/demo/legacy/__init__.py
athenaCL/demo/legacy/demo01.xml
athenaCL/demo/legacy/demo03.xml
athenaCL/demo/legacy/demo05.xml
athenaCL/demo/legacy/spectrum01.txt
athenaCL/demo/manual/tutorial03-a.xml
athenaCL/demo/manual/tutorial04-a.xml
athenaCL/demo/manual/tutorial04-b.xml
athenaCL/demo/manual/tutorial04-c.xml
athenaCL/demo/manual/tutorial04-d.xml
athenaCL/demo/manual/tutorial05-a.xml
athenaCL/demo/manual/tutorial05-b.xml
athenaCL/demo/manual/tutorial05-c.xml
athenaCL/demo/manual/tutorial05-d.xml
athenaCL/demo/manual/tutorial05-e.xml
athenaCL/demo/manual/tutorial06-a.xml
athenaCL/demo/manual/tutorial06-b.xml
athenaCL/demo/manual/tutorial06-c.xml
athenaCL/demo/manual/tutorial07-a.py
athenaCL/demo/midi/__init__.py
athenaCL/demo/midi/script01a.mid
athenaCL/demo/midi/script01a.py
