Metadata-Version: 1.0
Name: athenaCL
Version: 2.0.0a15
Summary: modular poly-paradigm algorithmic music composition in a cross-platform interactive command-line environment.
Home-page: http://www.athenacl.org
Author: Christopher Ariza
Author-email: ariza@flexatone.net
License: GPL
Download-URL: http://athenacl.googlecode.com/files/athenaCL-2.0.0a15.tar.gz
Platform: UNKNOWN
Classifier: Development Status :: 5 - Production/Stable
Classifier: Environment :: Console
Classifier: Intended Audience :: End Users/Desktop
Classifier: Intended Audience :: Developers
Classifier: License :: OSI Approved :: GNU General Public License (GPL)
Classifier: Natural Language :: English
Classifier: Operating System :: MacOS
Classifier: Operating System :: Microsoft :: Windows
Classifier: Operating System :: POSIX
Classifier: Operating System :: OS Independent
Classifier: Programming Language :: Python
Classifier: Topic :: Multimedia :: Sound/Audio
Classifier: Topic :: Artistic Software
